synthmob/__init__.py
synthmob/building.py
synthmob/metadata.py
synthmob/od.py
synthmob/pois.py
synthmob/raster.py
synthmob/roads.py
synthmob/spark.py
synthmob/utils.py
synthmob-0.0.2.dist-info/METADATA
synthmob-0.0.2.dist-info/WHEEL
synthmob-0.0.2.dist-info/licenses/LICENSE
synthmob-0.0.2.dist-info/RECORD
