Metadata-Version: 2.4
Name: synthmob
Version: 0.0.2
Summary: Parametric generator of synthetic gps data.
Project-URL: Homepage, https://github.com/lwdovico/synthmob
Author-email: Ludovico Lemma <lwdovico@protonmail.com>
License-Expression: MIT
License-File: LICENSE
Classifier: Programming Language :: Python :: 3
Requires-Python: >=3.8
Requires-Dist: apache-sedona==1.6.1
Requires-Dist: dask-expr==1.1.21
Requires-Dist: geomob>=0.0.9
Requires-Dist: joblib>=1.4.2
Requires-Dist: momepy==0.9.1
Requires-Dist: osmnx==2.0.1
Requires-Dist: pyproj==3.7.0
Requires-Dist: pyspark==3.4.1
Requires-Dist: python-igraph==0.11.8
Requires-Dist: rasterio==1.4.3
Requires-Dist: rioxarray==0.18.1
Requires-Dist: scikit-learn>=1.6.1
Requires-Dist: tqdm>=4.67.1
Requires-Dist: xarray-spatial==0.4.0
Requires-Dist: xee==0.0.19
